Metadata-Version: 1.0
Name: Jigglypuff-GroupF
Version: 0.1
Summary: Python Packaging Starting Kit - Simple Structure to creater your own package - for training purposes!
Home-page: https://github.com/hana-am/Jigglypuff_GroupF
Author: Hana AlMashari
Author-email: hanaahmad.m@gmail.com
License: MIT
Platform: UNKNOWN
